{
  "name": "left_kick",
  "next": "walk_ready",
  "poses": [
    {
      "joints": {
        "left_ankle_pitch": -4.833984375,
        "left_ankle_roll": -36.03515625,
        "left_elbow": -51.943359375,
        "left_hip_pitch": 25.751953125,
        "left_hip_roll": -5.361328125,
        "left_hip_yaw": -2.8125,
        "left_knee": -11.162109375,
        "left_shoulder_pitch": 17.9296875,
        "left_shoulder_roll": 19.951171875,
        "neck_pitch": 0,
        "neck_yaw": 0,
        "right_ankle_pitch": 26.103515625,
        "right_ankle_roll": -11.25,
        "right_elbow": 51.943359375,
        "right_hip_pitch": -39.55078125,
        "right_hip_roll": 2.548828125,
        "right_hip_yaw": 2.98828125,
        "right_knee": 51.6796875,
        "right_shoulder_pitch": -14.94140625,
        "right_shoulder_roll": -32.958984375
      },
      "name": "step_0",
      "pause": 0.3,
      "speed": 0.01,
      "time": 0.5
    },
    {
      "joints": {
        "left_ankle_pitch": -78.22265625,
        "left_ankle_roll": -5.361328125,
        "left_elbow": -51.943359375,
        "left_hip_pitch": 25.3125,
        "left_hip_roll": -1.93359375,
        "left_hip_yaw": 0.3515625,
        "left_knee": -94.21875,
        "left_shoulder_pitch": 17.9296875,
        "left_shoulder_roll": 19.951171875,
        "neck_pitch": 0,
        "neck_yaw": 0,
        "right_ankle_pitch": 26.103515625,
        "right_ankle_roll": -11.25,
        "right_elbow": 51.943359375,
        "right_hip_pitch": -39.55078125,
        "right_hip_roll": 2.548828125,
        "right_hip_yaw": 2.98828125,
        "right_knee": 51.6796875,
        "right_shoulder_pitch": -14.94140625,
        "right_shoulder_roll": -32.958984375
      },
      "name": "step_1",
      "pause": 0.1,
      "speed": 0.01,
      "time": 0.3
    },
    {
      "joints": {
        "left_ankle_pitch": 4.482421875,
        "left_ankle_roll": -16.875,
        "left_elbow": -51.943359375,
        "left_hip_pitch": 76.81640625,
        "left_hip_roll": -5.888671875,
        "left_hip_yaw": 0.791015625,
        "left_knee": -52.119140625,
        "left_shoulder_pitch": 17.9296875,
        "left_shoulder_roll": 19.951171875,
        "neck_pitch": 0,
        "neck_yaw": 0,
        "right_ankle_pitch": 26.103515625,
        "right_ankle_roll": -11.25,
        "right_elbow": 51.943359375,
        "right_hip_pitch": -39.55078125,
        "right_hip_roll": 2.548828125,
        "right_hip_yaw": 2.98828125,
        "right_knee": 51.6796875,
        "right_shoulder_pitch": -14.94140625,
        "right_shoulder_roll": -32.958984375
      },
      "name": "step_2",
      "pause": 0,
      "speed": 0,
      "time": 0.2
    },
    {
      "joints": {
        "left_ankle_pitch": -23.115234375,
        "left_ankle_roll": -18.369140625,
        "left_elbow": -51.943359375,
        "left_hip_pitch": 45.703125,
        "left_hip_roll": -2.28515625,
        "left_hip_yaw": 0.791015625,
        "left_knee": -50.888671875,
        "left_shoulder_pitch": 17.9296875,
        "left_shoulder_roll": 19.951171875,
        "neck_pitch": 0,
        "neck_yaw": 0,
        "right_ankle_pitch": 26.103515625,
        "right_ankle_roll": -11.25,
        "right_elbow": 51.943359375,
        "right_hip_pitch": -39.55078125,
        "right_hip_roll": 2.548828125,
        "right_hip_yaw": 2.98828125,
        "right_knee": 51.6796875,
        "right_shoulder_pitch": -14.94140625,
        "right_shoulder_roll": -32.958984375
      },
      "name": "step_3",
      "pause": 0.2,
      "speed": 0.01,
      "time": 0.4
    }
  ],
  "start_delay": 1.5,
  "stop_delay": 0,
  "time_based": true
}
