{
  "move": {
    "min_x": 15,
    "max_x": 25,
    "max_a": 5,
    "max_y": 20
  },
  "backward": {
    "min_x": -10,
    "max_x": -20,
    "max_a": 6
  },
  "rotate": {
    "max_a": 8,
    "max_delta_direction": 14
  },
  "follow": {
    "min_x": 7,
    "max_x": 25,
    "min_ly": 12,
    "max_ly": 20,
    "min_ry": -20,
    "max_ry": -12,
    "max_a": 7,
    "l_a_offset": 0,
    "r_a_offset": 0,
    "min_tilt_": -55,
    "pan_ratio": 0,
    "y_move": false
  },
  "skew": {
    "max_x": 12,
    "max_a": 14,
    "tilt": -30,
    "pan_comp": 27,
    "delta_direction_comp": 45
  },
  "dribble": {
    "min_x": -20,
    "max_x": 20,
    "min_ly": 15,
    "max_ly": 20,
    "min_ry": -15,
    "max_ry": -20,
    "max_a": 7,
    "pan_comp": 8
  },
  "pivot": {
    "min_x": -6,
    "max_x": 12,
    "max_ly": 25,
    "max_ry": -25,
    "max_a": 5,
    "target_tilt": -65,
    "pan_range_ratio": 0.3,
    "max_delta_direction": 10,
    "pan_range_a_speed": 15,
    "pivot_stop_limit": 60
  },
  "position": {
    "min_x": -5,
    "max_x": 12,
    "min_ly": 14,
    "max_ly": 15,
    "min_ry": -14,
    "max_ry": -15,
    "max_a": 7,
    "min_delta_tilt": 2,
    "min_delta_pan": 2,
    "min_delta_pan_tilt": 3,
    "min_delta_direction": 10,
    "min_range_pan": -24,
    "center_range_pan": 19,
    "max_range_pan": 24,
    "min_range_tilt": -71,
    "max_range_tilt": -68,
    "min_dynamic_range_pan": -40,
    "max_dynamic_range_pan": 40,
    "min_dynamic_range_tilt": -40,
    "max_dynamic_range_tilt": 40
  },
  "left_kick": {
    "target_pan": 23,
    "target_tilt": -65
  },
  "right_kick": {
    "target_pan": -23,
    "target_tilt": -65
  }
}
