{
  "name": "left_sidekick90",
  "next": "walk_ready",
  "poses": [
    {
      "joints": {
        "left_ankle_pitch": 9.316406,
        "left_ankle_roll": -39.375,
        "left_elbow": -39.990234,
        "left_hip_pitch": 10.019531,
        "left_hip_roll": -5.361328,
        "left_hip_yaw": -1.933594,
        "left_knee": 0.175781,
        "left_shoulder_pitch": 0.966797,
        "left_shoulder_roll": 26.982422,
        "neck_pitch": 0,
        "neck_yaw": 0,
        "right_ankle_pitch": 23.994141,
        "right_ankle_roll": -9.492188,
        "right_elbow": 39.990234,
        "right_hip_pitch": -37.441406,
        "right_hip_roll": 7.558594,
        "right_hip_yaw": 0.966797,
        "right_knee": 48.515625,
        "right_shoulder_pitch": -0.966797,
        "right_shoulder_roll": -23.994141
      },
      "name": "step_0",
      "pause": 0,
      "speed": 0.015,
      "time": 0.55
    },
    {
      "joints": {
        "left_ankle_pitch": -84.638672,
        "left_ankle_roll": -1.669922,
        "left_elbow": -39.990234,
        "left_hip_pitch": -4.746094,
        "left_hip_roll": -12.216797,
        "left_hip_yaw": -12.480469,
        "left_knee": -80.332031,
        "left_shoulder_pitch": 0.966797,
        "left_shoulder_roll": 26.982422,
        "neck_pitch": 0,
        "neck_yaw": 0,
        "right_ankle_pitch": 23.994141,
        "right_ankle_roll": -9.492188,
        "right_elbow": 39.990234,
        "right_hip_pitch": -37.441406,
        "right_hip_roll": 7.558594,
        "right_hip_yaw": 0.966797,
        "right_knee": 48.515625,
        "right_shoulder_pitch": -0.966797,
        "right_shoulder_roll": -23.994141
      },
      "name": "step_1",
      "pause": 0.2,
      "speed": 0.015,
      "time": 0.35
    },
    {
      "joints": {
        "left_ankle_pitch": 14.589844,
        "left_ankle_roll": -28.212891,
        "left_elbow": -39.990234,
        "left_hip_pitch": 53.349609,
        "left_hip_roll": -21.181641,
        "left_hip_yaw": 38.496094,
        "left_knee": -17.841797,
        "left_shoulder_pitch": 0.966797,
        "left_shoulder_roll": 26.982422,
        "neck_pitch": 0,
        "neck_yaw": 0,
        "right_ankle_pitch": 23.994141,
        "right_ankle_roll": -9.492188,
        "right_elbow": 39.990234,
        "right_hip_pitch": -31.904297,
        "right_hip_roll": 7.558594,
        "right_hip_yaw": 0.966797,
        "right_knee": 48.515625,
        "right_shoulder_pitch": -0.966797,
        "right_shoulder_roll": -23.994141
      },
      "name": "step_2",
      "pause": 0,
      "speed": 0.04,
      "time": 0.45
    },
    {
      "joints": {
        "left_ankle_pitch": -20.214844,
        "left_ankle_roll": -17.490234,
        "left_elbow": -39.990234,
        "left_hip_pitch": 27.773438,
        "left_hip_roll": -2.636719,
        "left_hip_yaw": 1.40625,
        "left_knee": -34.453125,
        "left_shoulder_pitch": 0.966797,
        "left_shoulder_roll": 26.982422,
        "neck_pitch": 0,
        "neck_yaw": 0,
        "right_ankle_pitch": 23.994141,
        "right_ankle_roll": -9.492188,
        "right_elbow": 39.990234,
        "right_hip_pitch": -37.441406,
        "right_hip_roll": 7.558594,
        "right_hip_yaw": 0.966797,
        "right_knee": 48.515625,
        "right_shoulder_pitch": -0.966797,
        "right_shoulder_roll": -23.994141
      },
      "name": "step_3",
      "pause": 0,
      "speed": 0.025,
      "time": 0.4
    }
  ],
  "start_delay": 1.5,
  "stop_delay": 0,
  "time_based": true
}
